pyminflux/__init__.py
pyminflux/analysis/__init__.py
pyminflux/analysis/_analysis.py
pyminflux/base/__init__.py
pyminflux/base/_base.py
pyminflux/correct/__init__.py
pyminflux/correct/_correct.py
pyminflux/fourier/__init__.py
pyminflux/fourier/_fourier.py
pyminflux/main.py
pyminflux/plugin/__init__.py
pyminflux/plugin/_plugin.py
pyminflux/plugin/_plugin_manager.py
pyminflux/plugin/_tools.py
pyminflux/processor/__init__.py
pyminflux/processor/_processor.py
pyminflux/reader/__init__.py
pyminflux/reader/_factory.py
pyminflux/reader/_msr_reader.py
pyminflux/reader/_pmx_reader.py
pyminflux/reader/_reader.py
pyminflux/reader/_reader_v2.py
pyminflux/reader/metadata/__init__.py
pyminflux/reader/metadata/_metadata.py
pyminflux/reader/util/__init__.py
pyminflux/reader/util/_util.py
pyminflux/render/__init__.py
pyminflux/render/_render.py
pyminflux/resources.py
pyminflux/resources.qrc
pyminflux/settings/__init__.py
pyminflux/settings/_settings.py
pyminflux/settings/_update_settings.py
pyminflux/spatial/__init__.py
pyminflux/spatial/_spatial.py
pyminflux/threads/__init__.py
pyminflux/threads/common.py
pyminflux/threads/frc.py
pyminflux/threads/update.py
pyminflux/ui/__init__.py
pyminflux/ui/analyzer.py
pyminflux/ui/analyzer.ui
pyminflux/ui/assets/Logo_v3.icns
pyminflux/ui/assets/Logo_v3.ico
pyminflux/ui/assets/Logo_v3.png
pyminflux/ui/assets/Logo_v3_small.png
pyminflux/ui/assets/create_resources.sh
pyminflux/ui/assets/png_to_icns.sh
pyminflux/ui/color_unmixer.py
pyminflux/ui/color_unmixer.ui
pyminflux/ui/colorbar.py
pyminflux/ui/colors.py
pyminflux/ui/custom_dialogs/__init__.py
pyminflux/ui/custom_dialogs/_custom_dialogs.py
pyminflux/ui/dataviewer.py
pyminflux/ui/emittingstream.py
pyminflux/ui/frc_tool.py
pyminflux/ui/frc_tool.ui
pyminflux/ui/helpers/__init__.py
pyminflux/ui/helpers/_helpers.py
pyminflux/ui/histogram_plotter.py
pyminflux/ui/histogram_plotter.ui
pyminflux/ui/icons/icon.png
pyminflux/ui/importer.py
pyminflux/ui/importer.ui
pyminflux/ui/main_window.py
pyminflux-0.6.0.dist-info/LICENSE.txt
pyminflux-0.6.0.dist-info/METADATA
pyminflux-0.6.0.dist-info/WHEEL
pyminflux-0.6.0.dist-info/entry_points.txt
pyminflux-0.6.0.dist-info/RECORD
