Metadata-Version: 2.3
Name: pyminflux
Version: 0.6.0
Summary: Reader, processor, and viewer of MINFLUX raw data.
License: Apache-2.0
Keywords: MINFLUX,Visualization,Filtering,Analysis,Python
Author: Aaron Ponti
Author-email: aaron.ponti@bsse.ethz.ch
Requires-Python: >=3.10,<3.13
Classifier: Development Status :: 5 - Production/Stable
Classifier: Intended Audience :: Developers
Classifier: Intended Audience :: End Users/Desktop
Classifier: Intended Audience :: Science/Research
Classifier: License :: OSI Approved :: Apache Software License
Classifier: Operating System :: MacOS :: MacOS X
Classifier: Operating System :: Microsoft :: Windows
Classifier: Operating System :: POSIX :: Linux
Classifier: Programming Language :: Python :: 3
Classifier: Programming Language :: Python :: 3.10
Classifier: Programming Language :: Python :: 3.11
Classifier: Programming Language :: Python :: 3.12
Classifier: Topic :: Scientific/Engineering
Requires-Dist: h5py (>=3.11.0,<4.0.0)
Requires-Dist: natsort (>=8.4.0,<9.0.0)
Requires-Dist: numpy (>=2.0.0,<3.0.0)
Requires-Dist: pandas (>=2.2.3,<3.0.0)
Requires-Dist: pyarrow (>=19.0.1,<20.0.0)
Requires-Dist: pyqtgraph (>=0.13.7,<0.14.0)
Requires-Dist: pyside6 (<6.8.0)
Requires-Dist: requests (>=2.32,<3.0)
Requires-Dist: scikit-learn (>=1.5.0,<2.0.0)
Requires-Dist: scipy (>=1.14.0,<2.0.0)
Requires-Dist: vispy (>=0.14.3,<0.15.0)
Requires-Dist: zarr (<3.0)
Project-URL: Bug Tracker, https://github.com/bsse-scf/pyMINFLUX/issues
Project-URL: Documentation, https://github.com/bsse-scf/pyMINFLUX/wiki
Project-URL: Repository, https://github.com/bsse-scf/pyMINFLUX
